setup.py
sunnyday/__init__.py
sunnyday/sunnyday.py
sunnyday_weather_forecast_IOY.egg-info/PKG-INFO
sunnyday_weather_forecast_IOY.egg-info/SOURCES.txt
sunnyday_weather_forecast_IOY.egg-info/dependency_links.txt
sunnyday_weather_forecast_IOY.egg-info/top_level.txt