Metadata-Version: 2.1
Name: sunnyday-weather-forecast-IOY
Version: 2.0.0
Summary: weather report package
Home-page: UNKNOWN
Author: konstantinosalexiou
Author-email: alexiou_kon@yahoo.gr
License: MIT
Keywords: weather,forecast,openweather
Platform: UNKNOWN
